Workbook

Sheet Model
A1: ConZ — 30-day revenue model (editable)
A2: Blue cells are inputs: change them and every black formula recalculates. Yellow = key assumption to confirm. Units: US$.
A4: Inputs | C4: Conservative | D4: Base | E4: Optimistic | F4: Notes / source
A5: Active verified drivers with a truck | C5: 3 | D5: 5 | E5: 8 | F5: Assumption. Production 24/10: 5 verified, 2 with a truck saved.
A6: Active suppliers / loading points | C6: 1 | D6: 2 | E6: 3 | F6: Assumption. Production: 2 verified sites near Marondera.
A7: Qualified customer leads in 30 days | C7: 25 | D7: 45 | E7: 80 | F7: Assumption: people with a real load need in the next 30 days.
A8: Lead → first booking conversion | C8: 0.15 | D8: 0.25 | E8: 0.35 | F8: Assumption.
A9: Bookings per converted customer (repeat loads) | C9: 1 | D9: 1.5 | E9: 2.5 | F9: Assumption: contractors reorder; house builders often 1.
A10: Job completion rate (booked → delivered) | C10: 0.7 | D10: 0.8 | E10: 0.9 | F10: Assumption.
A11: Average eligible job value (materials + transport) | C11: 250 | D11: 350 | E11: 450 | F11: Assumption. Live examples: $207 for 12 m³ quarry dust; $400 for 12 m³ river sand.
A12: Commission rate | C12: 0.07 | D12: 0.07 | E12: 0.07 | F12: Founder decision: 7% of materials + transport.
A13: First completed job free per new driver (1 = on, 0 = off) | C13: 1 | D13: 1 | E13: 1 | F13: Current policy in the database. Set 0 to see its cost.
A14: Commission collected / earned | C14: 0.9 | D14: 0.97 | E14: 0.99 | F14: Prepaid reserve makes collection near-certain; gap = disputes, failed top-ups.
A15: Refunds, disputes, write-offs (share of commission) | C15: 0.05 | D15: 0.03 | E15: 0.02 | F15: Assumption.
A16: Share of commission credit bought through Paynow | C16: 0.5 | D16: 0.5 | E16: 0.5 | F16: Rest by manual transfer (no gateway fee).
... A21: Other essential costs (POTRAZ Tier 1 licence, misc.) | C21: 60 | D21: 60 | E21: 60 | F21: SI 155/2024: Tier 1 licence $50/yr; $10 misc.
A23: Results (30 days) | C23: Conservative | D23: Base | E23: Optimistic | F23: What it means
A24: Customers who book | C24: =C7*C8 -> 3.75 | D24: =D7*D8 -> 11.25 | E24: =E7*E8 -> 28
A25: Jobs booked | C25: =C24*C9 -> 3.75 | D25: =D24*D9 -> 16.875 | E25: =E24*E9 -> 70
A26: Booked job value | C26: =C25*C11 -> 937.5 | D26: =D25*D11 -> 5906.25 | E26: =E25*E11 -> 31500 | F26: Customers' money to drivers/suppliers — never ConZ's
A27: Jobs completed | C27: =C25*C10 -> 2.625 | D27: =D25*D10 -> 13.5 | E27: =E25*E10 -> 63
A28: Of which free first jobs | C28: =IF(C13=1,MIN(C5,C27),0) -> 2.625 | D28: =IF(D13=1,MIN(D5,D27),0) -> 5 | E28: =IF(E13=1,MIN(E5,E27),0) -> 8 | F28: Earn no commission
A29: Commission-bearing jobs | C29: =MAX(C27-C28,0) -> 0 | D29: =MAX(D27-D28,0) -> 8.5 | E29: =MAX(E27-E28,0) -> 55
A30: Commission earned | C30: =C29*C11*C12 -> 0 | D30: =D29*D11*D12 -> 208.25 | E30: =E29*E11*E12 -> 1732.5 | F30: Recognised at verified completion
A31: Commission collected | C31: =C30*C14*(1-C15) -> 0 | D31: =D30*D14*(1-D15) -> 195.94242 | E31: =E30*E14*(1-E15) -> 1680.8715 | F31: Applied from driver credit
A32: Payment processing fees | C32: =IF(C31>0,C31*C16*C17+IF(C16>0,C18*C19,0),0) -> 0 | D32: =IF(D31>0,D31*D16*D17+IF(D16>0,D18*D19,0),0) -> 36.44928 | E32: =IF(E31>0,E31*E16*E17+IF(E16>0,E18*E19,0),0) -> 55.010894
A33: Net commission cash | C33: =C31-C32 -> 0 | D33: =D31-D32 -> 159.49314 | E33: =E31-E32 -> 1625.8606
A34: Outreach + essential costs | C34: =C20+C21 -> 180 | D34: =D20+D21 -> 210 | E34: =E20+E21 -> 260 | F34: Cash needed before revenue arrives
A35: Net cash result for the month | C35: =C33-C34 -> -180 | D35: =D33-D34 -> -50.506855 | E35: =E33-E34 -> 1365.8606 | F35: Unrestricted company cash change
A36: Completed jobs per driver | C36: =IF(C5>0,C27/C5,0) -> 0.875 | D36: =IF(D5>0,D27/D5,0) -> 2.7 | E36: =IF(E5>0,E27/E5,0) -> 7.875 | F36: Check it is realistic (truck days)
A37: Driver credit held at month end (liability, not profit) | C37: =C5*C11*C12 -> 52.5 | D37: =D5*D11*D12 -> 122.5 | E37: =E5*E11*E12 -> 252 | F37: Assumes each driver keeps one job's commission in credit
A39: Definitions: booked job value and driver credit are not ConZ revenue. Commission is earned at verified completion and is company cash only once the top-up has settled to ConZ's bank account.

Sheet Targets
A1: Jobs needed to collect a commission target in 30 days
A2: Uses Base-case rate, collection, write-off, completion, conversion, repeat and driver count from the Model sheet (green = linked).
B3: Average job value →
A4: Commission target ($) | B4: 200 | C4: 350 | D4: 500
A5: Target $300: commission-bearing jobs | B5: =ROUNDUP($F5/(B$4*Model!$D$12*Model!$D$14*(1-Model!$D$15)),0) -> 23 | C5: =ROUNDUP($F5/(C$4*Model!$D$12*Model!$D$14*(1-Model!$D$15)),0) -> 14 | D5: =ROUNDUP($F5/(D$4*Model!$D$12*Model!$D$14*(1-Model!$D$15)),0) -> 10 | F5: 300 | G5: ← target (edit)
A6: + free first jobs (one per driver) | B6: =IF(Model!$D$13=1,Model!$D$5,0) -> 5 | C6: =IF(Model!$D$13=1,Model!$D$5,0) -> 5 | D6: =IF(Model!$D$13=1,Model!$D$5,0) -> 5
A7: = completed jobs needed | B7: =B5+B6 -> 28 | C7: =C5+C6 -> 19 | D7: =D5+D6 -> 15
A8: bookings needed | B8: =ROUNDUP(B7/Model!$D$10,0) -> 35 | C8: =ROUNDUP(C7/Model!$D$10,0) -> 24 | D8: =ROUNDUP(D7/Model!$D$10,0) -> 19
A9: qualified leads needed | B9: =ROUNDUP(B8/(Model!$D$8*Model!$D$9),0) -> 94 | C9: =ROUNDUP(C8/(Model!$D$8*Model!$D$9),0) -> 64 | D9: =ROUNDUP(D8/(Model!$D$8*Model!$D$9),0) -> 51
A11: Target $500: commission-bearing jobs | B11: =ROUNDUP($F11/(B$4*Model!$D$12*Model!$D$14*(1-Model!$D$15)),0) -> 38 | C11: =ROUNDUP($F11/(C$4*Model!$D$12*Model!$D$14*(1-Model!$D$15)),0) -> 22 | D11: =ROUNDUP($F11/(D$4*Model!$D$12*Model!$D$14*(1-Model!$D$15)),0) -> 16 | F11: 500 | G11: ← target (edit)
A12: + free first jobs (one per driver) | B12: =IF(Model!$D$13=1,Model!$D$5,0) -> 5 | C12: =IF(Model!$D$13=1,Model!$D$5,0) -> 5 | D12: =IF(Model!$D$13=1,Model!$D$5,0) -> 5
A13: = completed jobs needed | B13: =B11+B12 -> 43 | C13: =C11+C12 -> 27 | D13: =D11+D12 -> 21
A14: bookings needed | B14: =ROUNDUP(B13/Model!$D$10,0) -> 54 | C14: =ROUNDUP(C13/Model!$D$10,0) -> 34 | D14: =ROUNDUP(D13/Model!$D$10,0) -> 27
A15: qualified leads needed | B15: =ROUNDUP(B14/(Model!$D$8*Model!$D$9),0) -> 144 | C15: =ROUNDUP(C14/(Model!$D$8*Model!$D$9),0) -> 91 | D15: =ROUNDUP(D14/(Model!$D$8*Model!$D$9),0) -> 72
A17: Target $1000: commission-bearing jobs | B17: =ROUNDUP($F17/(B$4*Model!$D$12*Model!$D$14*(1-Model!$D$15)),0) -> 76 | C17: =ROUNDUP($F17/(C$4*Model!$D$12*Model!$D$14*(1-Model!$D$15)),0) -> 44 | D17: =ROUNDUP($F17/(D$4*Model!$D$12*Model!$D$14*(1-Model!$D$15)),0) -> 31 | F17: 1000 | G17: ← target (edit)
A18: + free first jobs (one per driver) | B18: =IF(Model!$D$13=1,Model!$D$5,0) -> 5 | C18: =IF(Model!$D$13=1,Model!$D$5,0) -> 5 | D18: =IF(Model!$D$13=1,Model!$D$5,0) -> 5
A19: = completed jobs needed | B19: =B17+B18 -> 81 | C19: =C17+C18 -> 49 | D19: =D17+D18 -> 36
A20: bookings needed | B20: =ROUNDUP(B19/Model!$D$10,0) -> 102 | C20: =ROUNDUP(C19/Model!$D$10,0) -> 62 | D20: =ROUNDUP(D19/Model!$D$10,0) -> 45
A21: qualified leads needed | B21: =ROUNDUP(B20/(Model!$D$8*Model!$D$9),0) -> 272 | C21: =ROUNDUP(C20/(Model!$D$8*Model!$D$9),0) -> 166 | D21: =ROUNDUP(D20/(Model!$D$8*Model!$D$9),0) -> 120
